nusa/_3d_experimental.py
nusa/__init__.py
nusa/_experimental.py
nusa/_lib.py
nusa/_mesh.py
nusa/core.py
nusa/element.py
nusa/graph.py
nusa/io.py
nusa/lib.py
nusa/mesh.py
nusa/model.py
nusa/templates.py
nusa-0.2.0.dist-info/METADATA
nusa-0.2.0.dist-info/RECORD
nusa-0.2.0.dist-info/WHEEL
nusa-0.2.0.dist-info/top_level.txt
