Metadata-Version: 2.1
Name: nusa
Version: 0.2.0
Summary: Numerical Structural Analysis in Python using the FEM
Home-page: https://github.com/JorgeDeLosSantos/nusa
Author: Pedro Jorge De Los Santos
Author-email: delossantosmfq@gmail.com
License: MIT
Keywords: Structural Analysis,Finite Element Analysis,Mechanical Engineering
Platform: UNKNOWN
Classifier: Development Status :: 2 - Pre-Alpha
Classifier: Intended Audience :: Education
Classifier: Intended Audience :: Developers
Classifier: License :: OSI Approved :: MIT License
Classifier: Operating System :: OS Independent
Classifier: Programming Language :: Python
Classifier: Programming Language :: Python :: 3
Classifier: Programming Language :: Python :: Implementation :: CPython
